tap_pushbullet/__init__.py
tap_pushbullet/__main__.py
tap_pushbullet/client.py
tap_pushbullet/streams.py
tap_pushbullet/tap.py
tap_pushbullet-0.5.4.dist-info/METADATA
tap_pushbullet-0.5.4.dist-info/WHEEL
tap_pushbullet-0.5.4.dist-info/entry_points.txt
tap_pushbullet-0.5.4.dist-info/RECORD
