Metadata-Version: 2.4
Name: tap-pushbullet
Version: 0.5.4
Summary: Singer tap for Pushbullet, built with the Meltano SDK for Singer Taps.
Project-URL: Documentation, https://github.com/reservoir-data/tap-pushbullet#readme
Project-URL: Homepage, https://github.com/reservoir-data/tap-pushbullet
Project-URL: Repository, https://github.com/reservoir-data/tap-pushbullet
Author-email: Edgar Ramírez-Mondragón <edgarrm358@gmail.com>
License-Expression: Apache-2.0
Keywords: ELT,Pushbullet,singer.io
Classifier: Programming Language :: Python :: 3 :: Only
Classifier: Programming Language :: Python :: 3.12
Classifier: Programming Language :: Python :: 3.13
Classifier: Programming Language :: Python :: 3.14
Requires-Python: >=3.12
Requires-Dist: backoff~=2.2.1
Requires-Dist: requests-cache<2,>=1.1
Requires-Dist: singer-sdk~=0.51.0
